metacv/__init__.py
metacv/app/__init__.py
metacv/app/classification.py
metacv/app/detection.py
metacv/app/face.py
metacv/app/face_detection.py
metacv/app/face_embedding.py
metacv/app/obb_detection.py
metacv/app/person_detection.py
metacv/app/segment.py
metacv/model_zoo/__init__.py
metacv/utils/__init__.py
metacv/utils/draw.py
metacv/utils/face_align.py
metacv/utils/general.py
meta_cv-0.1.11.dist-info/METADATA
meta_cv-0.1.11.dist-info/WHEEL
meta_cv-0.1.11.dist-info/top_level.txt
meta_cv-0.1.11.dist-info/zip-safe
meta_cv-0.1.11.dist-info/RECORD
