Metadata-Version: 2.1
Name: meta-cv
Version: 0.1.11
Summary: Meta CV Toolkit
Home-page: https://github.com/CachCheng/metacv
Author: CachCheng
Author-email: tkggpdc2007@163.com
License: Apache-2.0
Platform: UNKNOWN
Requires-Dist: opencv-python
Requires-Dist: numpy
Requires-Dist: scikit-image
Requires-Dist: setuptools
